[
  {
    "id": "hapoel-15hxnnei15pxmsb8inei15xx",
    "category": "hapoel",
    "title": "בלעדי | עומר פרץ סיכם לשנתיים נוספות בהפועל פ\"ת וישודרג ב־33 אחוז",
    "source": "ynet Sport Israel Soccer",
    "sourceUrl": "https://www.ynet.co.il/sport/israelisoccer/article/b1viu00rn11g",
    "sourceKind": "secondary",
    "sourceType": "secondary",
    "sourceStrength": "medium",
    "publishedAt": "2026-04-11",
    "fresh": true,
    "signalPositive": true,
    "signalNegative": false,
    "verificationCount": 1,
    "collectedAt": "2026-04-11T15:47:58.347Z",
    "certainty": "נמוכה",
    "summary": "עדכון מועדון: בלעדי | עומר פרץ סיכם לשנתיים נוספות בהפועל פ\"ת וישודרג ב־33 אחוז.",
    "why": "זה עדכון חדש עם חשיבות ישירה להפועל פתח תקווה.",
    "hype": "נמוכה",
    "worth": "כן",
    "action": "לקרוא",
    "score": 27
  },
  {
    "id": "hapoel-15txldet16lxqidxntev16lx",
    "category": "hapoel",
    "title": "הודעת מועדון 09 04",
    "source": "Hapoel PT News",
    "sourceUrl": "https://www.hapoelpt.com/post/הודעת-מועדון-09-04",
    "sourceKind": "primary",
    "sourceType": "primary",
    "sourceStrength": "high",
    "publishedAt": "2026-04-11",
    "fresh": true,
    "signalPositive": true,
    "signalNegative": false,
    "verificationCount": 1,
    "collectedAt": "2026-04-11T15:47:58.347Z",
    "certainty": "מאומת חלקית",
    "summary": "עדכון מועדון: הודעת מועדון 09 04.",
    "why": "זה עדכון חדש עם חשיבות ישירה להפועל פתח תקווה.",
    "hype": "נמוכה",
    "worth": "כן",
    "action": "לקרוא",
    "score": 22
  }
]