[
  {
    "id": "israel-iteu15zxmdec15qg16dxk9ei",
    "category": "israel",
    "title": "\"הלילה נדע\": טראמפ מחכה למכתב מאיראן ומאיים ב\"פרויקט חירות פלוס\"",
    "source": "Israel Hayom News",
    "sourceUrl": "https://www.israelhayom.co.il/news/world-news/usa/article/20497128",
    "sourceKind": "secondary",
    "sourceType": "secondary",
    "sourceStrength": "medium",
    "publishedAt": "2026-05-09T00:00:00",
    "fresh": true,
    "signalPositive": true,
    "signalNegative": false,
    "verificationCount": 1,
    "collectedAt": "2026-05-09T04:30:09.192Z",
    "fixture": false,
    "synthetic": false,
    "summary": "\"הלילה נדע\": טראמפ מחכה למכתב מאיראן ומאיים ב\"פרויקט חירות פלוס\"",
    "why": "למה זה חשוב",
    "certainty": "נמוכה",
    "score": 23,
    "publishedLabel": "09.05.2026, 00:00"
  },
  {
    "id": "israel-15jxqneq157xpdog17txlnek",
    "category": "israel",
    "title": "טראמפ: ״הפסקת אש ל-3 ימים״, זלנסקי הטריל: ״מרשה לקיים את המצעד במוסקבה״",
    "source": "Israel Hayom News",
    "sourceUrl": "https://www.israelhayom.co.il/news/world-news/europe/article/20496838",
    "sourceKind": "secondary",
    "sourceType": "secondary",
    "sourceStrength": "medium",
    "publishedAt": "2026-05-09T00:00:00",
    "fresh": true,
    "signalPositive": true,
    "signalNegative": false,
    "verificationCount": 1,
    "collectedAt": "2026-05-09T04:30:09.192Z",
    "fixture": false,
    "synthetic": false,
    "summary": "טראמפ: ״הפסקת אש ל-3 ימים״, זלנסקי הטריל: ״מרשה לקיים את המצעד במוסקבה״",
    "why": "למה זה חשוב",
    "certainty": "נמוכה",
    "score": 23,
    "publishedLabel": "09.05.2026, 00:00"
  },
  {
    "id": "israel-16dxqdez15ag15dxqneuiter",
    "category": "israel",
    "title": "נשיא ארה\"ב הודיע על הפסקת אש במלחמה בין רוסיה לאוקראינה לרגל ציון יום",
    "source": "Israel Hayom News",
    "sourceUrl": "https://www.israelhayom.co.il/news/world-news/europe/article/20496838",
    "sourceKind": "secondary",
    "sourceType": "secondary",
    "sourceStrength": "medium",
    "publishedAt": "2026-05-09T00:00:00",
    "fresh": true,
    "signalPositive": true,
    "signalNegative": false,
    "verificationCount": 1,
    "collectedAt": "2026-05-09T04:30:09.192Z",
    "fixture": false,
    "synthetic": false,
    "summary": "נשיא ארה\"ב הודיע על הפסקת אש במלחמה בין רוסיה לאוקראינה לרגל ציון יום",
    "why": "למה זה חשוב",
    "certainty": "נמוכה",
    "score": 23,
    "publishedLabel": "09.05.2026, 00:00"
  },
  {
    "id": "israel-16hxmdee15xxnydxkter15xx",
    "category": "israel",
    "title": "סימון גבולות ופירוק חיזבאללה: הפרטים החדשים על השיחות בין ישראל ללבנון",
    "source": "Israel Hayom News",
    "sourceUrl": "https://www.israelhayom.co.il/news/world-news/middle-east/article/20496577",
    "sourceKind": "secondary",
    "sourceType": "secondary",
    "sourceStrength": "medium",
    "publishedAt": "2026-05-09T00:00:00",
    "fresh": true,
    "signalPositive": true,
    "signalNegative": false,
    "verificationCount": 1,
    "collectedAt": "2026-05-09T04:30:09.192Z",
    "fixture": false,
    "synthetic": false,
    "summary": "סימון גבולות ופירוק חיזבאללה: הפרטים החדשים על השיחות בין ישראל ללבנון",
    "why": "למה זה חשוב",
    "certainty": "נמוכה",
    "score": 23,
    "publishedLabel": "09.05.2026, 00:00"
  },
  {
    "id": "israel-15hxqnen16ig15txlneh15zx",
    "category": "israel",
    "title": "ברקע ההסלמה מול חיזבאללה: נקבע המועד לסבב השיחות בין ישראל ללבנון",
    "source": "Israel Hayom News",
    "sourceUrl": "https://www.israelhayom.co.il/news/world-news/middle-east/article/20496179",
    "sourceKind": "secondary",
    "sourceType": "secondary",
    "sourceStrength": "medium",
    "publishedAt": "2026-05-09T00:00:00",
    "fresh": true,
    "signalPositive": true,
    "signalNegative": false,
    "verificationCount": 1,
    "collectedAt": "2026-05-09T04:30:09.192Z",
    "fixture": false,
    "synthetic": false,
    "summary": "ברקע ההסלמה מול חיזבאללה: נקבע המועד לסבב השיחות בין ישראל ללבנון",
    "why": "למה זה חשוב",
    "certainty": "נמוכה",
    "score": 23,
    "publishedLabel": "09.05.2026, 00:00"
  },
  {
    "id": "israel-15dxqneuiterineq16fxmdez",
    "category": "israel",
    "title": "ארה\"ב תקיים בשבוע הבא סבב שיחות בין ישראל ללבנון, כהמשך לזה שהתקיים בא",
    "source": "Israel Hayom News",
    "sourceUrl": "https://www.israelhayom.co.il/news/world-news/middle-east/article/20496179",
    "sourceKind": "secondary",
    "sourceType": "secondary",
    "sourceStrength": "medium",
    "publishedAt": "2026-05-09T00:00:00",
    "fresh": true,
    "signalPositive": true,
    "signalNegative": false,
    "verificationCount": 1,
    "collectedAt": "2026-05-09T04:30:09.192Z",
    "fixture": false,
    "synthetic": false,
    "summary": "ארה\"ב תקיים בשבוע הבא סבב שיחות בין ישראל ללבנון, כהמשך לזה שהתקיים בא",
    "why": "למה זה חשוב",
    "certainty": "נמוכה",
    "score": 23,
    "publishedLabel": "09.05.2026, 00:00"
  }
]